pose_estimation/__init__.py
tests/__init__.py
pose_estimation-0.0.1.dist-info/LICENSE
pose_estimation-0.0.1.dist-info/METADATA
pose_estimation-0.0.1.dist-info/WHEEL
pose_estimation-0.0.1.dist-info/top_level.txt
pose_estimation-0.0.1.dist-info/RECORD
